{"cenXB1ELJMFcruuHIDAvAw==":"webbackground!.gif","GGjLNnqRnLgbC+mrtvGytw==":"bwlogoweb.gif","XTrj8MSFNC5g8ikIpv60Zw==":"bwlogoweb.png","ertUXFCfgyvsAwNdN2Z2Yg==":"brandingdistplayweb.gif","ilq+UF7XH1xdLeGQ1Ar44A==":"webbackground!.png","J5YDHr5RaHmf9JvKa6rEew==":"brandingdistplayweb.png","SB97fo2ApKBZo3FRY7WLQg==":"cuddlecoatsweb.gif","pm9+QylbW0p97gWgoFtMPg==":"cuddlecoatsbrandingweb.gif","83/CHN8Yc7w75HoZHNqPgQ==":"flowerpattern001web.gif","7ZxVzfijxihgOzmOE5a3hA==":"flowerpattern001web.png","ilNPIjMyBFKA5Jyt0IPzsA==":"flowerpattern001web-1.gif","trgoZFJEPAHKvCklElO4AQ==":"mbr-1920x1280.jpg","EDOFe5c0XTdYx8rrz27NaQ==":"flowerpattern001web-1.png","7PoUN6kyevfn9+hk+pMFLg==":"flowerpattern001web-2.gif","MXusAw4FySStOoncH6dsfw==":"mbr-1-1920x1280.jpg","Ndt3+Th520Ec6rEhs1KsNg==":"webflower.gif","QNnzfU7xRiyeFxVR6TZVbw==":"cuddlecoatsbrandingweb-1.gif","pE0DOhfAISGUI1gNEC/5yA==":"cuddlecoatsbrandingweb-1.png","NTDMCtpuRITk8sqT/ZOWbw==":"cuddlecoatsbrandingweb-2.gif","YPTFYWed6hIlRDF0kBJojg==":"flowerweb1.gif","gHyZbzDpZcC+9V7AIBk+1w==":"flowerweb2.gif","nkrTvWa2PQEVOhXAp4Sybw==":"flowerweb3.gif","iacnanVwR9r5vJXexBSEnA==":"pattern002web.gif","H5kJT3ymdCI4mXrRpwNzEA==":"pattern001web.gif","pItQyt10fFULLaYcm6Zweg==":"brandingdistplayweb-1.png"}